{
  "task": "xml_upload_to_aws", 
  "depends_on": [
    "completed@prepare_metadata_xml"
  ], 
  "tool": "upload_to_aws", 
  "command": "upload_to_aws.py", 
  "input": {
    "file_name": "bundle.EGAR00001110172.xml", 
    "object_id": "fb0cfe6b-df02-5a74-8e5b-4c1dce94283a", 
    "file_md5sum": "{{xml_file_md5sum@prepare_metadata_xml}}", 
    "file": "{{xml_file@prepare_metadata_xml}}", 
    "file_size": "{{xml_file_size@prepare_metadata_xml}}", 
    "bundle_id": "EGAR00001110172", 
    "project_code": "LINC-JP"
  }, 
  "runtime": {
    "docker": null
  }
}