{
  "task": "xml_upload_to_aws", 
  "depends_on": [
    "completed@prepare_metadata_xml"
  ], 
  "tool": "upload_to_aws", 
  "command": "upload_to_aws.py", 
  "output": [
    {
      "idx_file_size": 0, 
      "idx_file_md5sum": null, 
      "_jt_": {
        "worker_id": "worker.1499457181.561298b6.host.231181a3.10.10.1.7", 
        "workflow_version": "0.6.7", 
        "jt_version": "0.1.0rc9", 
        "task_state": "completed"
      }, 
      "idx_file": null, 
      "allowed_upload": true, 
      "file_md5sum": "0fc3cb3b5bc9ae6ec8d2f2454bce2e9b", 
      "file": "/home/ubuntu/jtracker/worker.1499457181.561298b6.host.231181a3.10.10.1.7/job.EGAR00001110481.LINC-JP.HCC14T.EGAN00001085971/task.prepare_metadata_xml/bundle.EGAR00001110481.xml", 
      "file_size": 3663, 
      "runtime": {
        "task_start": 1500049811, 
        "task_stop": 1500049818
      }
    }
  ], 
  "input": {
    "file_name": "bundle.EGAR00001110481.xml", 
    "object_id": "dddf296c-58de-5109-b903-49fc8d9eb051", 
    "file_md5sum": "0fc3cb3b5bc9ae6ec8d2f2454bce2e9b", 
    "file": "/home/ubuntu/jtracker/worker.1499457181.561298b6.host.231181a3.10.10.1.7/job.EGAR00001110481.LINC-JP.HCC14T.EGAN00001085971/task.prepare_metadata_xml/bundle.EGAR00001110481.xml", 
    "file_size": 3663, 
    "bundle_id": "EGAR00001110481", 
    "project_code": "LINC-JP"
  }, 
  "runtime": {
    "docker": null
  }
}