{
  "task": "xml_file_upload", 
  "depends_on": [
    "completed@xml_upload_to_aws", 
    "completed@prepare_metadata_xml"
  ], 
  "tool": "upload", 
  "command": "upload.py", 
  "output": [
    {
      "_jt_": {
        "worker_id": "worker.1498856079.c6a1acff.host.231181a3.10.10.1.7", 
        "workflow_version": "0.6.6", 
        "jt_version": "0.1.0rc9", 
        "task_state": "completed"
      }, 
      "runtime": {
        "task_start": 1498964684, 
        "task_stop": 1498964700
      }
    }
  ], 
  "input": {
    "file_name": "bundle.EGAR00001113145.xml", 
    "object_id": "19d32897-3ffd-5a78-bdf6-cd685dd01c50", 
    "file_md5sum": "58c4267f481ebefa317bdcb32e97d6d9", 
    "file": "/home/ubuntu/jtracker/worker.1498856079.c6a1acff.host.231181a3.10.10.1.7/job.EGAR00001113145.LINC-JP.HCC51T.EGAN00001086002/task.prepare_metadata_xml/bundle.EGAR00001113145.xml", 
    "file_size": 3659, 
    "bundle_id": "EGAR00001113145"
  }, 
  "runtime": {
    "docker": null
  }
}