{
  "task": "xml_upload_to_aws", 
  "depends_on": [
    "completed@prepare_metadata_xml"
  ], 
  "tool": "upload_to_aws", 
  "command": "upload_to_aws.py", 
  "output": [
    {
      "_jt_": {
        "worker_id": "worker.1499458089.619df4d0.host.76674056.10.10.0.19", 
        "workflow_version": "0.6.7", 
        "jt_version": "0.1.0rc9", 
        "task_state": "failed"
      }
    }
  ], 
  "input": {
    "file_name": "bundle.EGAR00001116156.xml", 
    "object_id": "97968232-ff32-56a0-b462-9bbd02096233", 
    "file_md5sum": "d05fb24cca76562e9b45f7fadb1f92f4", 
    "file": "/home/ubuntu/jtracker/worker.1499458089.619df4d0.host.76674056.10.10.0.19/job.EGAR00001116156.LINC-JP.HCC94T.EGAN00001086040/task.prepare_metadata_xml/bundle.EGAR00001116156.xml", 
    "file_size": 3663, 
    "bundle_id": "EGAR00001116156", 
    "project_code": "LINC-JP"
  }, 
  "runtime": {
    "docker": null
  }
}