{
  "task": "delete_encrypted_file", 
  "depends_on": [
    "completed@md5sum_check_decrypt.EGAF00000143348", 
    "completed@download.EGAF00000143348"
  ], 
  "tool": "delete_file", 
  "command": "delete_file.py", 
  "input": {
    "file": "/home/ubuntu/jtracker/worker.1500386341.51a53461.host.76674056.10.10.0.19/job.EGAR00001072732.CLLE-ES.019-01-1TR.EGAN00001036970/task.download.EGAF00000143348/ef30369dccf0169b34e2ef20ff382663.626WGAAXX_3_2_sequence.txt.gz"
  }, 
  "runtime": {
    "docker": null
  }
}