{
  "task": "xml_file_upload", 
  "depends_on": [
    "completed@xml_upload_to_aws", 
    "completed@prepare_metadata_xml"
  ], 
  "tool": "upload", 
  "command": "upload.py", 
  "input": {
    "file_name": "bundle.EGAR00001198963.xml", 
    "object_id": "2b1b1a02-6d9b-59ad-ab7d-81b4148fca6c", 
    "file_md5sum": "fd3c90aded5552f1d44b4230b73ead1f", 
    "file": "/home/ubuntu/jtracker/worker.1500386341.51a53461.host.76674056.10.10.0.19/job.EGAR00001198963.LINC-JP.HCC173T.EGAN00001196921/task.prepare_metadata_xml/bundle.EGAR00001198963.xml", 
    "file_size": 3507, 
    "bundle_id": "EGAR00001198963"
  }, 
  "runtime": {
    "docker": null
  }
}