{
  "task": "xml_upload_to_aws", 
  "depends_on": [
    "completed@prepare_metadata_xml"
  ], 
  "tool": "upload_to_aws", 
  "command": "upload_to_aws.py", 
  "input": {
    "file_name": "bundle.EGAR00001112309.xml", 
    "object_id": "672b41ac-97df-5aa2-9127-7936289650a5", 
    "file_md5sum": "47455eaf05f1313ee31ffa64abb1b185", 
    "file": "/home/ubuntu/jtracker/worker.1499457181.561298b6.host.231181a3.10.10.1.7/job.EGAR00001112309.LINC-JP.HCC35T.EGAN00001085990/task.prepare_metadata_xml/bundle.EGAR00001112309.xml", 
    "file_size": 3665, 
    "bundle_id": "EGAR00001112309", 
    "project_code": "LINC-JP"
  }, 
  "runtime": {
    "docker": null
  }
}