{
  "task": "xml_file_upload", 
  "depends_on": [
    "completed@xml_upload_to_aws", 
    "completed@prepare_metadata_xml"
  ], 
  "tool": "upload", 
  "command": "upload.py", 
  "output": [
    {
      "_jt_": {
        "worker_id": "worker.1499457181.561298b6.host.231181a3.10.10.1.7", 
        "workflow_version": "0.6.7", 
        "jt_version": "0.1.0rc9", 
        "task_state": "completed"
      }, 
      "runtime": {
        "task_start": 1500273764, 
        "task_stop": 1500273781
      }
    }
  ], 
  "input": {
    "file_name": "bundle.EGAR00001112707.xml", 
    "object_id": "54089766-39c3-54cd-9371-b6c0df5c137f", 
    "file_md5sum": "8945ab15ab09f3dd12f843eb0d9aa829", 
    "file": "/home/ubuntu/jtracker/worker.1499457181.561298b6.host.231181a3.10.10.1.7/job.EGAR00001112707.LINC-JP.HCC40T.EGAN00001085995/task.prepare_metadata_xml/bundle.EGAR00001112707.xml", 
    "file_size": 3665, 
    "bundle_id": "EGAR00001112707"
  }, 
  "runtime": {
    "docker": null
  }
}