{
  "task": "xml_file_upload", 
  "depends_on": [
    "completed@xml_upload_to_aws", 
    "completed@prepare_metadata_xml"
  ], 
  "tool": "upload", 
  "command": "upload.py", 
  "output": [
    {
      "_jt_": {
        "worker_id": "worker.1500386341.51a53461.host.76674056.10.10.0.19", 
        "workflow_version": "0.6.7", 
        "jt_version": "0.1.0rc9", 
        "task_state": "completed"
      }, 
      "runtime": {
        "task_start": 1501011000, 
        "task_stop": 1501011017
      }
    }
  ], 
  "input": {
    "file_name": "bundle.EGAR00001256664.xml", 
    "object_id": "bfb3aad3-9310-5e8e-8616-fa218fe7b275", 
    "file_md5sum": "c01c08834ffed8eb1a31bd983cca7964", 
    "file": "/home/ubuntu/jtracker/worker.1500386341.51a53461.host.76674056.10.10.0.19/job.EGAR00001256664.BTCA-JP.BD40T.EGAN00001246844/task.prepare_metadata_xml/bundle.EGAR00001256664.xml", 
    "file_size": 3174, 
    "bundle_id": "EGAR00001256664"
  }, 
  "runtime": {
    "docker": null
  }
}