{
  "task": "xml_upload_to_aws", 
  "depends_on": [
    "completed@prepare_metadata_xml"
  ], 
  "tool": "upload_to_aws", 
  "command": "upload_to_aws.py", 
  "input": {
    "file_name": "bundle.EGAR00001112055.xml", 
    "object_id": "23ab9156-673f-5d6f-a07e-ae32b492a4f6", 
    "file_md5sum": "ff4db136c4a0fe2396245b4542566e9c", 
    "file": "/home/ubuntu/jtracker/worker.1499457181.561298b6.host.231181a3.10.10.1.7/job.EGAR00001112055.LINC-JP.HCC33T.EGAN00001085988/task.prepare_metadata_xml/bundle.EGAR00001112055.xml", 
    "file_size": 3663, 
    "bundle_id": "EGAR00001112055", 
    "project_code": "LINC-JP"
  }, 
  "runtime": {
    "docker": null
  }
}