{
  "task": "xml_file_upload", 
  "depends_on": [
    "completed@xml_upload_to_aws", 
    "completed@prepare_metadata_xml"
  ], 
  "tool": "upload", 
  "command": "upload.py", 
  "input": {
    "file_name": "bundle.EGAR00001108481.xml", 
    "object_id": "f0e3ab12-1cdc-5fe7-8d01-c38414ae3376", 
    "file_md5sum": "5e3200b658ecb0e111d6020bcf7a138b", 
    "file": "/home/ubuntu/jtracker/worker.1499457181.561298b6.host.231181a3.10.10.1.7/job.EGAR00001108481.LINC-JP.BN34T.EGAN00001085949/task.prepare_metadata_xml/bundle.EGAR00001108481.xml", 
    "file_size": 3659, 
    "bundle_id": "EGAR00001108481"
  }, 
  "runtime": {
    "docker": null
  }
}