{
  "task": "prepare_metadata_xml", 
  "depends_on": null, 
  "tool": "prepare_metadata_xml", 
  "command": "prepare_metadata_xml.py", 
  "output": [
    {
      "xml_file_md5sum": "e6e75e0f0ace31fcd9e95e5994646a95", 
      "xml_file_name": "bundle.EGAR00001112754.xml", 
      "xml_file": "/home/ubuntu/jtracker/worker.1500386341.51a53461.host.76674056.10.10.0.19/job.EGAR00001112754.LINC-JP.HCC41T.EGAN00001085996/task.prepare_metadata_xml/bundle.EGAR00001112754.xml", 
      "_jt_": {
        "worker_id": "worker.1500386341.51a53461.host.76674056.10.10.0.19", 
        "workflow_version": "0.6.7", 
        "jt_version": "0.1.0rc9", 
        "task_state": "completed"
      }, 
      "xml_file_size": 3659, 
      "runtime": {
        "task_start": 1500436819, 
        "task_stop": 1500436820
      }
    }
  ], 
  "input": {
    "ega_metadata_repo": "https://raw.githubusercontent.com/icgc-dcc/ega-file-transfer/master/ega_xml/v20170522", 
    "ega_metadata_file_name": "bundle.EGAR00001112754.xml", 
    "ega_study_id": "EGAS00001000389", 
    "ega_dataset_id": "EGAD00001000446", 
    "ega_sample_id": "EGAN00001085996", 
    "ega_analysis_id": null, 
    "ega_experiment_id": "EGAX00001109030", 
    "bundle_id": "EGAR00001112754", 
    "project_code": "LINC-JP", 
    "ega_run_id": "EGAR00001112754"
  }, 
  "runtime": {
    "docker": null
  }
}