{
  "task": "xml_file_upload", 
  "depends_on": [
    "completed@xml_upload_to_aws", 
    "completed@prepare_metadata_xml"
  ], 
  "tool": "upload", 
  "command": "upload.py", 
  "output": [
    {
      "_jt_": {
        "worker_id": "worker.1499716017.b5c22856.host.032f1807.10.10.0.3", 
        "workflow_version": "0.6.7", 
        "jt_version": "0.1.0rc9", 
        "task_state": "completed"
      }, 
      "runtime": {
        "task_start": 1499719437, 
        "task_stop": 1499719452
      }
    }
  ], 
  "input": {
    "file_name": "bundle.EGAR00001108876.xml", 
    "object_id": "c0184a41-c84f-56e0-9c16-4de9e46c99ff", 
    "file_md5sum": "dfcc33e04930ccc16b870db3ba037f6b", 
    "file": "/home/ubuntu/jtracker/worker.1499716017.b5c22856.host.032f1807.10.10.0.3/job.EGAR00001108876.LINC-JP.BN38T.EGAN00001085952/task.prepare_metadata_xml/bundle.EGAR00001108876.xml", 
    "file_size": 3659, 
    "bundle_id": "EGAR00001108876"
  }, 
  "runtime": {
    "docker": null
  }
}