{
  "task": "decryption", 
  "depends_on": [
    "completed@download.EGAF00000143345"
  ], 
  "tool": "decryption", 
  "command": "decryption.py", 
  "output": [
    {
      "_jt_": {
        "worker_id": "worker.1499457181.561298b6.host.231181a3.10.10.1.7", 
        "workflow_version": "0.6.7", 
        "jt_version": "0.1.0rc9", 
        "task_state": "completed"
      }, 
      "file_name": "f3e09d037370172f042b15b501951f1b.626WGAAXX_2_1_sequence.txt.gz", 
      "ega_file_id": "EGAF00000143345", 
      "object_id": "0a6dd71f-3b15-5a1e-b67a-fa1c3d7a2914", 
      "file_md5sum": "f3e09d037370172f042b15b501951f1b", 
      "file": "/home/ubuntu/jtracker/worker.1499457181.561298b6.host.231181a3.10.10.1.7/job.EGAR00001072731.CLLE-ES.018-0045-01TR.EGAN00001036969/task.decryption.EGAF00000143345/f3e09d037370172f042b15b501951f1b.626WGAAXX_2_1_sequence.txt.gz", 
      "file_size": 3116399365, 
      "runtime": {
        "task_start": 1500612377, 
        "task_stop": 1500612396
      }
    }
  ], 
  "input": {
    "file_name": "f3e09d037370172f042b15b501951f1b.626WGAAXX_2_1_sequence.txt.gz", 
    "file_md5sum": "f3e09d037370172f042b15b501951f1b", 
    "ega_file_id": "EGAF00000143345", 
    "object_id": "0a6dd71f-3b15-5a1e-b67a-fa1c3d7a2914", 
    "input_file": "/home/ubuntu/jtracker/worker.1499457181.561298b6.host.231181a3.10.10.1.7/job.EGAR00001072731.CLLE-ES.018-0045-01TR.EGAN00001036969/task.download.EGAF00000143345/f3e09d037370172f042b15b501951f1b.626WGAAXX_2_1_sequence.txt.gz"
  }, 
  "runtime": {
    "docker": null
  }
}