{
  "task": "xml_upload_to_aws", 
  "depends_on": [
    "completed@prepare_metadata_xml"
  ], 
  "tool": "upload_to_aws", 
  "command": "upload_to_aws.py", 
  "input": {
    "file_name": "bundle.EGAR00001261798.xml", 
    "object_id": "5a31ba84-5f20-5dbf-b4bd-4ac23147dcb3", 
    "file_md5sum": "6a1d6227d9d569e4bd8de115d4029cde", 
    "file": "/home/ubuntu/jtracker/worker.1502297095.05915f8b.host.032f1807.10.10.0.3/job.EGAR00001261798.BTCA-JP.BD178T.EGAN00001246978/task.prepare_metadata_xml/bundle.EGAR00001261798.xml", 
    "file_size": 3186, 
    "bundle_id": "EGAR00001261798", 
    "project_code": "BTCA-JP"
  }, 
  "runtime": {
    "docker": null
  }
}