{
  "task": "xml_file_upload", 
  "depends_on": [
    "completed@xml_upload_to_aws", 
    "completed@prepare_metadata_xml"
  ], 
  "tool": "upload", 
  "command": "upload.py", 
  "output": [
    {
      "_jt_": {
        "worker_id": "worker.1498856079.c6a1acff.host.231181a3.10.10.1.7", 
        "workflow_version": "0.6.6", 
        "jt_version": "0.1.0rc9", 
        "task_state": "completed"
      }, 
      "runtime": {
        "task_start": 1499213012, 
        "task_stop": 1499213026
      }
    }
  ], 
  "input": {
    "file_name": "bundle.EGAR00001116740.xml", 
    "object_id": "b2145251-6d32-56be-9ae5-174a2108bd42", 
    "file_md5sum": "7c3ca5635f2d92d50e23469ef3767bde", 
    "file": "/home/ubuntu/jtracker/worker.1498856079.c6a1acff.host.231181a3.10.10.1.7/job.EGAR00001116740.LINC-JP.HCC98T.EGAN00001086043/task.prepare_metadata_xml/bundle.EGAR00001116740.xml", 
    "file_size": 3667, 
    "bundle_id": "EGAR00001116740"
  }, 
  "runtime": {
    "docker": null
  }
}