{
  "task": "xml_upload_to_aws", 
  "depends_on": [
    "completed@prepare_metadata_xml"
  ], 
  "tool": "upload_to_aws", 
  "command": "upload_to_aws.py", 
  "input": {
    "file_name": "bundle.EGAR00001110772.xml", 
    "object_id": "41d9a84d-9291-5ed3-a945-947b5a4e3199", 
    "file_md5sum": "72a4e2c37fcc1bb6ae8e1388a024bd5f", 
    "file": "/home/ubuntu/jtracker/worker.1499716017.b5c22856.host.032f1807.10.10.0.3/job.EGAR00001110772.LINC-JP.HCC17T.EGAN00001085974/task.prepare_metadata_xml/bundle.EGAR00001110772.xml", 
    "file_size": 3667, 
    "bundle_id": "EGAR00001110772", 
    "project_code": "LINC-JP"
  }, 
  "runtime": {
    "docker": null
  }
}