{
  "task": "xml_upload_to_aws", 
  "depends_on": [
    "completed@prepare_metadata_xml"
  ], 
  "tool": "upload_to_aws", 
  "command": "upload_to_aws.py", 
  "input": {
    "file_name": "bundle.EGAR00001256381.xml", 
    "object_id": "177daa00-a5b4-5ff4-94fe-3a505e829e3a", 
    "file_md5sum": "3840516c04ed0fb5346b5c3f901381db", 
    "file": "/home/ubuntu/jtracker/worker.1500386341.51a53461.host.76674056.10.10.0.19/job.EGAR00001256381.BTCA-JP.BD33T.EGAN00001246837/task.prepare_metadata_xml/bundle.EGAR00001256381.xml", 
    "file_size": 3174, 
    "bundle_id": "EGAR00001256381", 
    "project_code": "BTCA-JP"
  }, 
  "runtime": {
    "docker": null
  }
}