{
  "task": "xml_upload_to_aws", 
  "depends_on": [
    "completed@prepare_metadata_xml"
  ], 
  "tool": "upload_to_aws", 
  "command": "upload_to_aws.py", 
  "input": {
    "file_name": "bundle.EGAR00001198993.xml", 
    "object_id": "bc5c3d90-cd87-5386-8bfb-a3ca170ac977", 
    "file_md5sum": "7ebea58887e72285d29156e145063b56", 
    "file": "/home/ubuntu/jtracker/worker.1499457181.561298b6.host.231181a3.10.10.1.7/job.EGAR00001198993.LINC-JP.HCC174T.EGAN00001196922/task.prepare_metadata_xml/bundle.EGAR00001198993.xml", 
    "file_size": 3505, 
    "bundle_id": "EGAR00001198993", 
    "project_code": "LINC-JP"
  }, 
  "runtime": {
    "docker": null
  }
}