{
  "task": "xml_file_upload", 
  "depends_on": [
    "completed@xml_upload_to_aws", 
    "completed@prepare_metadata_xml"
  ], 
  "tool": "upload", 
  "command": "upload.py", 
  "output": [
    {
      "_jt_": {
        "worker_id": "worker.1502211234.caa1d114.host.032f1807.10.10.0.3", 
        "workflow_version": "0.6.7", 
        "jt_version": "0.1.0rc9", 
        "task_state": "completed"
      }, 
      "runtime": {
        "task_start": 1502242982, 
        "task_stop": 1502242997
      }
    }
  ], 
  "input": {
    "file_name": "bundle.EGAR00001261741.xml", 
    "object_id": "bc8f9bae-463d-5a4e-9f13-55dc9fb7a8e3", 
    "file_md5sum": "e4c5e68afe5f39b1fd732e92527162d1", 
    "file": "/home/ubuntu/jtracker/worker.1502211234.caa1d114.host.032f1807.10.10.0.3/job.EGAR00001261741.BTCA-JP.BD177T.EGAN00001246977/task.prepare_metadata_xml/bundle.EGAR00001261741.xml", 
    "file_size": 3186, 
    "bundle_id": "EGAR00001261741"
  }, 
  "runtime": {
    "docker": null
  }
}