{
  "task": "xml_upload_to_aws", 
  "depends_on": [
    "completed@prepare_metadata_xml"
  ], 
  "tool": "upload_to_aws", 
  "command": "upload_to_aws.py", 
  "input": {
    "file_name": "bundle.EGAR00001108359.xml", 
    "object_id": "b9b6d401-c64c-5052-b35a-a91f1f9c50d8", 
    "file_md5sum": "28b576dcbd27a4f68b522b40b962045f", 
    "file": "/home/ubuntu/jtracker/worker.1498856079.c6a1acff.host.231181a3.10.10.1.7/job.EGAR00001108359.LINC-JP.BN33T.EGAN00001085948/task.prepare_metadata_xml/bundle.EGAR00001108359.xml", 
    "file_size": 3659, 
    "bundle_id": "EGAR00001108359", 
    "project_code": "LINC-JP"
  }, 
  "runtime": {
    "docker": null
  }
}