{
  "task": "xml_upload_to_aws", 
  "depends_on": [
    "completed@prepare_metadata_xml"
  ], 
  "tool": "upload_to_aws", 
  "command": "upload_to_aws.py", 
  "input": {
    "file_name": "bundle.EGAR00001029535.xml", 
    "object_id": "2e2cf96d-bff6-51d9-9927-3e4acfdcc9af", 
    "file_md5sum": "b3058820bfb7cb465c48a6be6422ddd0", 
    "file": "/home/ubuntu/jtracker/worker.1502744356.15f99eee.host.032f1807.10.10.0.3/job.EGAR00001029535.BRCA-UK.PD4094b.EGAN00001000885/task.prepare_metadata_xml/bundle.EGAR00001029535.xml", 
    "file_size": 4067, 
    "bundle_id": "EGAR00001029535", 
    "project_code": "BRCA-UK"
  }, 
  "runtime": {
    "docker": null
  }
}