{
  "task": "xml_upload_to_aws", 
  "depends_on": [
    "completed@prepare_metadata_xml"
  ], 
  "tool": "upload_to_aws", 
  "command": "upload_to_aws.py", 
  "input": {
    "file_name": "bundle.EGAR00001261213.xml", 
    "object_id": "ce19e128-3a06-5d6e-8408-25c3a93957c2", 
    "file_md5sum": "371a029df9529ddad9f52361711f3770", 
    "file": "/home/ubuntu/jtracker/worker.1502211234.caa1d114.host.032f1807.10.10.0.3/job.EGAR00001261213.BTCA-JP.BD164T.EGAN00001246964/task.prepare_metadata_xml/bundle.EGAR00001261213.xml", 
    "file_size": 3186, 
    "bundle_id": "EGAR00001261213", 
    "project_code": "BTCA-JP"
  }, 
  "runtime": {
    "docker": null
  }
}