{
  "task": "xml_upload_to_aws", 
  "depends_on": [
    "completed@prepare_metadata_xml"
  ], 
  "tool": "upload_to_aws", 
  "command": "upload_to_aws.py", 
  "input": {
    "file_name": "bundle.EGAR00001198868.xml", 
    "object_id": "76b2bfee-503c-59cd-ab34-5d3da487d11f", 
    "file_md5sum": "e2f72ee252328d7f7d41681ca0590aa6", 
    "file": "/home/ubuntu/jtracker/worker.1499716017.b5c22856.host.032f1807.10.10.0.3/job.EGAR00001198868.LINC-JP.HCC172T.EGAN00001196920/task.prepare_metadata_xml/bundle.EGAR00001198868.xml", 
    "file_size": 3505, 
    "bundle_id": "EGAR00001198868", 
    "project_code": "LINC-JP"
  }, 
  "runtime": {
    "docker": null
  }
}