{
  "task": "xml_file_upload", 
  "depends_on": [
    "completed@xml_upload_to_aws", 
    "completed@prepare_metadata_xml"
  ], 
  "tool": "upload", 
  "command": "upload.py", 
  "input": {
    "file_name": "bundle.EGAR00001257631.xml", 
    "object_id": "040ca8a8-1b09-502a-8396-1a5a00302b55", 
    "file_md5sum": "efafc4ddc71739e214ad04ffc5678bb7", 
    "file": "/home/ubuntu/jtracker/worker.1499716017.b5c22856.host.032f1807.10.10.0.3/job.EGAR00001257631.BTCA-JP.BD63T.EGAN00001246867/task.prepare_metadata_xml/bundle.EGAR00001257631.xml", 
    "file_size": 3176, 
    "bundle_id": "EGAR00001257631"
  }, 
  "runtime": {
    "docker": null
  }
}