{
  "task": "xml_upload_to_aws", 
  "depends_on": [
    "completed@prepare_metadata_xml"
  ], 
  "tool": "upload_to_aws", 
  "command": "upload_to_aws.py", 
  "input": {
    "file_name": "bundle.EGAR00001198975.xml", 
    "object_id": "54a3e302-0044-535d-b8fc-45c36143fd9e", 
    "file_md5sum": "bfe1b297c8c30755c613fb81c91d21f3", 
    "file": "/home/ubuntu/jtracker/worker.1499716017.b5c22856.host.032f1807.10.10.0.3/job.EGAR00001198975.LINC-JP.HCC173T.EGAN00001196921/task.prepare_metadata_xml/bundle.EGAR00001198975.xml", 
    "file_size": 3507, 
    "bundle_id": "EGAR00001198975", 
    "project_code": "LINC-JP"
  }, 
  "runtime": {
    "docker": null
  }
}