{
  "task": "xml_upload_to_aws", 
  "depends_on": [
    "completed@prepare_metadata_xml"
  ], 
  "tool": "upload_to_aws", 
  "command": "upload_to_aws.py", 
  "output": [
    {
      "idx_file_size": 0, 
      "idx_file_md5sum": null, 
      "_jt_": {
        "worker_id": "worker.1499716017.b5c22856.host.032f1807.10.10.0.3", 
        "workflow_version": "0.6.7", 
        "jt_version": "0.1.0rc9", 
        "task_state": "completed"
      }, 
      "idx_file": null, 
      "allowed_upload": true, 
      "file_md5sum": "3fb31dbd5e18be6de49968e78417dee0", 
      "file": "/home/ubuntu/jtracker/worker.1499716017.b5c22856.host.032f1807.10.10.0.3/job.EGAR00001110596.LINC-JP.HCC15T.EGAN00001085972/task.prepare_metadata_xml/bundle.EGAR00001110596.xml", 
      "file_size": 3665, 
      "runtime": {
        "task_start": 1499911622, 
        "task_stop": 1499911628
      }
    }
  ], 
  "input": {
    "file_name": "bundle.EGAR00001110596.xml", 
    "object_id": "1ba4c2c8-9f95-56bc-875e-89a47d7a2cdf", 
    "file_md5sum": "3fb31dbd5e18be6de49968e78417dee0", 
    "file": "/home/ubuntu/jtracker/worker.1499716017.b5c22856.host.032f1807.10.10.0.3/job.EGAR00001110596.LINC-JP.HCC15T.EGAN00001085972/task.prepare_metadata_xml/bundle.EGAR00001110596.xml", 
    "file_size": 3665, 
    "bundle_id": "EGAR00001110596", 
    "project_code": "LINC-JP"
  }, 
  "runtime": {
    "docker": null
  }
}