{
  "task": "xml_upload_to_aws", 
  "depends_on": [
    "completed@prepare_metadata_xml"
  ], 
  "tool": "upload_to_aws", 
  "command": "upload_to_aws.py", 
  "input": {
    "file_name": "bundle.EGAR00001116097.xml", 
    "object_id": "afb46c6e-0524-5d6d-8ca0-3448b1ab6c7a", 
    "file_md5sum": "85fc444ade7905a5b7bd6de980d35b2e", 
    "file": "/home/ubuntu/jtracker/worker.1499458089.619df4d0.host.76674056.10.10.0.19/job.EGAR00001116097.LINC-JP.HCC94T.EGAN00001086040/task.prepare_metadata_xml/bundle.EGAR00001116097.xml", 
    "file_size": 3659, 
    "bundle_id": "EGAR00001116097", 
    "project_code": "LINC-JP"
  }, 
  "runtime": {
    "docker": null
  }
}