{
  "task": "xml_upload_to_aws", 
  "depends_on": [
    "completed@prepare_metadata_xml"
  ], 
  "tool": "upload_to_aws", 
  "command": "upload_to_aws.py", 
  "output": [
    {
      "idx_file_size": 0, 
      "idx_file_md5sum": null, 
      "_jt_": {
        "worker_id": "worker.1499716017.b5c22856.host.032f1807.10.10.0.3", 
        "workflow_version": "0.6.7", 
        "jt_version": "0.1.0rc9", 
        "task_state": "completed"
      }, 
      "idx_file": null, 
      "allowed_upload": true, 
      "file_md5sum": "cb4c7aae97fa4b0dbd5f5ce39608e6b5", 
      "file": "/home/ubuntu/jtracker/worker.1499716017.b5c22856.host.032f1807.10.10.0.3/job.EGAR00001116168.LINC-JP.HCC94T.EGAN00001086040/task.prepare_metadata_xml/bundle.EGAR00001116168.xml", 
      "file_size": 3663, 
      "runtime": {
        "task_start": 1500014576, 
        "task_stop": 1500014583
      }
    }
  ], 
  "input": {
    "file_name": "bundle.EGAR00001116168.xml", 
    "object_id": "6717f740-10f2-5f7c-a2e8-3cd21641dd49", 
    "file_md5sum": "cb4c7aae97fa4b0dbd5f5ce39608e6b5", 
    "file": "/home/ubuntu/jtracker/worker.1499716017.b5c22856.host.032f1807.10.10.0.3/job.EGAR00001116168.LINC-JP.HCC94T.EGAN00001086040/task.prepare_metadata_xml/bundle.EGAR00001116168.xml", 
    "file_size": 3663, 
    "bundle_id": "EGAR00001116168", 
    "project_code": "LINC-JP"
  }, 
  "runtime": {
    "docker": null
  }
}