{
  "task": "xml_file_upload", 
  "depends_on": [
    "completed@xml_upload_to_aws", 
    "completed@prepare_metadata_xml"
  ], 
  "tool": "upload", 
  "command": "upload.py", 
  "output": [
    {
      "_jt_": {
        "worker_id": "worker.1499716017.b5c22856.host.032f1807.10.10.0.3", 
        "workflow_version": "0.6.7", 
        "jt_version": "0.1.0rc9", 
        "task_state": "completed"
      }, 
      "runtime": {
        "task_start": 1500391085, 
        "task_stop": 1500391101
      }
    }
  ], 
  "input": {
    "file_name": "bundle.EGAR00001112859.xml", 
    "object_id": "ac6b6edf-d1a3-541b-8ccb-c6659ec6d163", 
    "file_md5sum": "411914f7eeac8db4631138e6c94d8682", 
    "file": "/home/ubuntu/jtracker/worker.1499716017.b5c22856.host.032f1807.10.10.0.3/job.EGAR00001112859.LINC-JP.HCC42T.EGAN00001085997/task.prepare_metadata_xml/bundle.EGAR00001112859.xml", 
    "file_size": 3663, 
    "bundle_id": "EGAR00001112859"
  }, 
  "runtime": {
    "docker": null
  }
}