{
  "task": "xml_upload_to_aws", 
  "depends_on": [
    "completed@prepare_metadata_xml"
  ], 
  "tool": "upload_to_aws", 
  "command": "upload_to_aws.py", 
  "input": {
    "file_name": "bundle.EGAR00001108068.xml", 
    "object_id": "f7d6ce03-e1b8-5631-afb7-77d2e76788c4", 
    "file_md5sum": "b5de3d8ec58c7b46dc13983e95ff54b9", 
    "file": "/home/ubuntu/jtracker/worker.1499716017.b5c22856.host.032f1807.10.10.0.3/job.EGAR00001108068.LINC-JP.BN28T.EGAN00001085944/task.prepare_metadata_xml/bundle.EGAR00001108068.xml", 
    "file_size": 3659, 
    "bundle_id": "EGAR00001108068", 
    "project_code": "LINC-JP"
  }, 
  "runtime": {
    "docker": null
  }
}