{
  "task": "xml_file_upload", 
  "depends_on": [
    "completed@xml_upload_to_aws", 
    "completed@prepare_metadata_xml"
  ], 
  "tool": "upload", 
  "command": "upload.py", 
  "output": [
    {
      "_jt_": {
        "worker_id": "worker.1500386341.51a53461.host.76674056.10.10.0.19", 
        "workflow_version": "0.6.7", 
        "jt_version": "0.1.0rc9", 
        "task_state": "completed"
      }, 
      "runtime": {
        "task_start": 1500412511, 
        "task_stop": 1500412526
      }
    }
  ], 
  "input": {
    "file_name": "bundle.EGAR00001116438.xml", 
    "object_id": "392f2b18-47cd-58c5-b147-461cd856487d", 
    "file_md5sum": "30457526b6606b59c3f05cbcaa555b1f", 
    "file": "/home/ubuntu/jtracker/worker.1500386341.51a53461.host.76674056.10.10.0.19/job.EGAR00001116438.LINC-JP.HCC97T.EGAN00001086042/task.prepare_metadata_xml/bundle.EGAR00001116438.xml", 
    "file_size": 3663, 
    "bundle_id": "EGAR00001116438"
  }, 
  "runtime": {
    "docker": null
  }
}