{
  "task": "xml_file_upload", 
  "depends_on": [
    "completed@xml_upload_to_aws", 
    "completed@prepare_metadata_xml"
  ], 
  "tool": "upload", 
  "command": "upload.py", 
  "input": {
    "file_name": "bundle.EGAR00001116041.xml", 
    "object_id": "deb9998e-4f1a-5142-bb4c-727023a04815", 
    "file_md5sum": "84f439a324056f4dc8d52e3d326871ab", 
    "file": "/home/ubuntu/jtracker/worker.1499716017.b5c22856.host.032f1807.10.10.0.3/job.EGAR00001116041.LINC-JP.HCC92T.EGAN00001086039/task.prepare_metadata_xml/bundle.EGAR00001116041.xml", 
    "file_size": 3663, 
    "bundle_id": "EGAR00001116041"
  }, 
  "runtime": {
    "docker": null
  }
}