{
  "task": "xml_upload_to_aws", 
  "depends_on": [
    "completed@prepare_metadata_xml"
  ], 
  "tool": "upload_to_aws", 
  "command": "upload_to_aws.py", 
  "input": {
    "file_name": "bundle.EGAR00001116088.xml", 
    "object_id": "5ce559a4-5159-52a3-992c-0a6347a93d86", 
    "file_md5sum": "23da6c2d189c0a9797a97da53acbe471", 
    "file": "/home/ubuntu/jtracker/worker.1500386341.51a53461.host.76674056.10.10.0.19/job.EGAR00001116088.LINC-JP.HCC92T.EGAN00001086039/task.prepare_metadata_xml/bundle.EGAR00001116088.xml", 
    "file_size": 3663, 
    "bundle_id": "EGAR00001116088", 
    "project_code": "LINC-JP"
  }, 
  "runtime": {
    "docker": null
  }
}