{
  "task": "xml_upload_to_aws", 
  "depends_on": [
    "completed@prepare_metadata_xml"
  ], 
  "tool": "upload_to_aws", 
  "command": "upload_to_aws.py", 
  "input": {
    "file_name": "bundle.EGAR00001113798.xml", 
    "object_id": "8c88ca7c-5df2-5a91-addb-ea989b7943e1", 
    "file_md5sum": "584f1c827ce1fd48820aa0eda8da9090", 
    "file": "/home/ubuntu/jtracker/worker.1498856079.c6a1acff.host.231181a3.10.10.1.7/job.EGAR00001113798.LINC-JP.HCC62T.EGAN00001086012/task.prepare_metadata_xml/bundle.EGAR00001113798.xml", 
    "file_size": 3665, 
    "bundle_id": "EGAR00001113798", 
    "project_code": "LINC-JP"
  }, 
  "runtime": {
    "docker": null
  }
}