{
  "task": "xml_upload_to_aws", 
  "depends_on": [
    "completed@prepare_metadata_xml"
  ], 
  "tool": "upload_to_aws", 
  "command": "upload_to_aws.py", 
  "input": {
    "file_name": "bundle.EGAR00001116063.xml", 
    "object_id": "ccfef45c-0639-5e8b-979c-8f423c7d7e83", 
    "file_md5sum": "d549ff2532325a91fcfd75d5e294c644", 
    "file": "/home/ubuntu/jtracker/worker.1499452616.e0598690.host.76674056.10.10.0.19/job.EGAR00001116063.LINC-JP.HCC92T.EGAN00001086039/task.prepare_metadata_xml/bundle.EGAR00001116063.xml", 
    "file_size": 3663, 
    "bundle_id": "EGAR00001116063", 
    "project_code": "LINC-JP"
  }, 
  "runtime": {
    "docker": null
  }
}