{
  "task": "xml_upload_to_aws", 
  "depends_on": [
    "completed@prepare_metadata_xml"
  ], 
  "tool": "upload_to_aws", 
  "command": "upload_to_aws.py", 
  "input": {
    "file_name": "bundle.EGAR00001256108.xml", 
    "object_id": "47886f0f-9a90-5277-9a86-ffda5ef9d46e", 
    "file_md5sum": "50f6dcefee08e1c1c9529fe2b5e787b8", 
    "file": "/home/ubuntu/jtracker/worker.1500386341.51a53461.host.76674056.10.10.0.19/job.EGAR00001256108.BTCA-JP.BD26T.EGAN00001246830/task.prepare_metadata_xml/bundle.EGAR00001256108.xml", 
    "file_size": 3174, 
    "bundle_id": "EGAR00001256108", 
    "project_code": "BTCA-JP"
  }, 
  "runtime": {
    "docker": null
  }
}