{
  "task": "xml_upload_to_aws", 
  "depends_on": [
    "completed@prepare_metadata_xml"
  ], 
  "tool": "upload_to_aws", 
  "command": "upload_to_aws.py", 
  "input": {
    "file_name": "bundle.EGAR00001113803.xml", 
    "object_id": "d6a44485-1cd4-583f-a573-e02c1e1e63ba", 
    "file_md5sum": "bdeaef8f20b371720d1285080761d2ff", 
    "file": "/home/ubuntu/jtracker/worker.1498856079.c6a1acff.host.231181a3.10.10.1.7/job.EGAR00001113803.LINC-JP.HCC62T.EGAN00001086012/task.prepare_metadata_xml/bundle.EGAR00001113803.xml", 
    "file_size": 3665, 
    "bundle_id": "EGAR00001113803", 
    "project_code": "LINC-JP"
  }, 
  "runtime": {
    "docker": null
  }
}