{
  "task": "xml_upload_to_aws", 
  "depends_on": [
    "completed@prepare_metadata_xml"
  ], 
  "tool": "upload_to_aws", 
  "command": "upload_to_aws.py", 
  "output": [
    {
      "idx_file_size": 0, 
      "idx_file_md5sum": null, 
      "_jt_": {
        "worker_id": "worker.1498856079.c6a1acff.host.231181a3.10.10.1.7", 
        "workflow_version": "0.6.6", 
        "jt_version": "0.1.0rc9", 
        "task_state": "completed"
      }, 
      "idx_file": null, 
      "allowed_upload": true, 
      "file_md5sum": "afe5b41369485196c99e6438aba5e3c7", 
      "file": "/home/ubuntu/jtracker/worker.1498856079.c6a1acff.host.231181a3.10.10.1.7/job.EGAR00001108654.LINC-JP.BN36T.EGAN00001085950/task.prepare_metadata_xml/bundle.EGAR00001108654.xml", 
      "file_size": 3659, 
      "runtime": {
        "task_start": 1499337129, 
        "task_stop": 1499337135
      }
    }
  ], 
  "input": {
    "file_name": "bundle.EGAR00001108654.xml", 
    "object_id": "17d81d7f-ec90-5686-99e3-78e5bddf03b0", 
    "file_md5sum": "afe5b41369485196c99e6438aba5e3c7", 
    "file": "/home/ubuntu/jtracker/worker.1498856079.c6a1acff.host.231181a3.10.10.1.7/job.EGAR00001108654.LINC-JP.BN36T.EGAN00001085950/task.prepare_metadata_xml/bundle.EGAR00001108654.xml", 
    "file_size": 3659, 
    "bundle_id": "EGAR00001108654", 
    "project_code": "LINC-JP"
  }, 
  "runtime": {
    "docker": null
  }
}